genome_cli/__init__.py
genome_cli-0.2.1.dist-info/METADATA
genome_cli-0.2.1.dist-info/WHEEL
genome_cli-0.2.1.dist-info/licenses/LICENSE
genome_cli-0.2.1.dist-info/RECORD
