Metadata-Version: 2.4
Name: genome-cli
Version: 0.2.1
Summary: CLI tool to analyze dbt manifest.json files - install via cargo
Project-URL: Homepage, https://github.com/stijnzanders/genome
Project-URL: Repository, https://github.com/stijnzanders/genome
Author: Stijn Zanders
License: Copyright (c) 2026 Stijn Zanders. All rights reserved.
License-File: LICENSE
Keywords: analytics,cli,dbt,manifest
Classifier: Development Status :: 3 - Alpha
Classifier: Environment :: Console
Classifier: Intended Audience :: Developers
Classifier: License :: Other/Proprietary License
Classifier: Programming Language :: Python :: 3
Classifier: Programming Language :: Rust
Classifier: Topic :: Software Development :: Build Tools
Requires-Python: >=3.9
